<?xml version='1.0' encoding='UTF-8'?>
<debate-format schema-version="2.2">
  <name>British Parliamentary</name>
  <version>1</version>
  <info>
    <region>World</region>
    <level>University</level>
    <used-at>World Universities Debating Championship</used-at>
    <used-at>European Universities Debating Championship</used-at>
    <used-at>Pan-African Universities Debating Championships</used-at>
    <description>Four teams of two, 7-minute speeches, POIs allowed</description>
  </info>
  <prep-time length="15:00"/>
  <speech-types>
    <speech-type ref="all" length="7:00" first-period="normal">
      <bell time="1:00" number="1" next-period="pois-allowed"/>
      <bell time="6:00" number="1" next-period="warning"/>
      <bell time="finish" number="2" next-period="overtime"/>
    </speech-type>
  </speech-types>
  <speeches>
    <speech type="all">
      <name>Prime Minister</name>
    </speech>
    <speech type="all">
      <name>Leader of the Opposition</name>
    </speech>
    <speech type="all">
      <name>Deputy Prime Minister</name>
    </speech>
    <speech type="all">
      <name>Deputy Leader of the Opposition</name>
    </speech>
    <speech type="all">
      <name>Member for the Government</name>
    </speech>
    <speech type="all">
      <name>Member for the Opposition</name>
    </speech>
    <speech type="all">
      <name>Government Whip</name>
    </speech>
    <speech type="all">
      <name>Opposition Whip</name>
    </speech>
  </speeches>
</debate-format>
