<?xml version='1.0' encoding='UTF-8'?>
<debate-format schema-version="2.1">
  <name>Canadian Parliamentary</name>
  <short-name>CP</short-name>
  <info>
    <region>Canada</region>
    <level>University</level>
    <used-at>Canadian National Debating Championship</used-at>
    <description>2 vs 2, POIs allowed, PM, MO, MC 7 minutes, LO 10 minutes, PM 3 minutes</description>
  </info>
  <period-types>
    <period-type ref="canadian.lo-rebuttal">
      <name>Canadian: Rebuttal time</name>
      <display>Rebuttal time</display>
      <default-bgcolor>#0C2F6E</default-bgcolor>
    </period-type>
  </period-types>
  <speech-types>
    <speech-type ref="constructive" length="7:00" first-period="normal">
      <bell time="1:00" number="1" next-period="pois-allowed"/>
      <bell time="6:00" number="1" next-period="warning"/>
      <bell time="finish" number="2" next-period="overtime"/>
    </speech-type>
    <speech-type ref="leader-opp" length="10:00" first-period="normal">
      <bell time="1:00" number="1" next-period="pois-allowed"/>
      <bell time="6:00" number="1" next-period="normal"/>
      <bell time="7:00" number="0" next-period="canadian.lo-rebuttal"/>
      <bell time="9:00" number="0" next-period="warning"/>
      <bell time="finish" number="2" next-period="overtime"/>
    </speech-type>
    <speech-type ref="pm-rebuttal" length="3:00" first-period="normal">
      <bell time="2:00" number="1" next-period="warning"/>
      <bell time="finish" number="2" next-period="overtime"/>
    </speech-type>
  </speech-types>
  <speeches>
    <speech type="constructive">
      <name>Prime Minister's Constructive</name>
    </speech>
    <speech type="constructive">
      <name>Member of the Opposition</name>
    </speech>
    <speech type="constructive">
      <name>Minister of the Crown</name>
    </speech>
    <speech type="leader-opp">
      <name>Leader of the Opposition</name>
    </speech>
    <speech type="pm-rebuttal">
      <name>Prime Minister's Rebuttal</name>
    </speech>
  </speeches>
</debate-format>
