<?xml version="1.0" encoding="UTF-8"?>
<debateformat name="Wellington Premier B">
	<info>
		<region>Wellington</region>
		<level>School</level>
		<usedat>Wellington Premier B grade</usedat>
		<desc>3 vs 3, 8-minute speeches, 4-minute replies, POIs allowed</desc>
	</info>

	<resource ref="#all">
		<period ref="initial" desc="First minute" bgcolor="#stay" />
		<period ref="warning" desc="Warning bell rung" bgcolor="#77ffcc00" />
		<period ref="overtime" desc="Overtime" bgcolor="#77ff0000" />
	</resource>

	<speechformat ref="substantive" length="8:00" firstperiod="initial">
		<period ref="pois-allowed" name="POIs allowed" bgcolor="#7700ff00" />
   		<bell time="1:00" number="1" nextperiod="pois-allowed" sound="#default" />
		<bell time="7:00" number="1" nextperiod="warning" sound="#default" />
		<bell time="finish" number="2" nextperiod="overtime" sound="#default" />
	</speechformat>
	
	<speechformat ref="reply" length="4:00" firstperiod="initial">
		<bell time="3:00" number="1" nextperiod="warning" sound="#default" />
		<bell time="finish" number="2" nextperiod="overtime" sound="#default" />
	</speechformat>
	
	<speeches>
		<speech name="1st Affirmative" format="substantive" />
		<speech name="1st Negative" format="substantive" />
		<speech name="2nd Affirmative" format="substantive" />
		<speech name="2nd Negative" format="substantive" />
		<speech name="3rd Affirmative" format="substantive" />
		<speech name="3rd Negative" format="substantive" />
		<speech name="Negative Leader's Reply" format="reply" />
		<speech name="Affirmative Leader's Reply" format="reply" />
	</speeches>
</debateformat>
